LICENSE
MANIFEST.in
README.md
pylintrc
setup.py
tox.ini
test/test_cli.py
test/test_list_handler.py
test/test_rulebook.py
test/test_validator.py
test/test_yaml_handler.py
yaml_rulz/__init__.py
yaml_rulz/cli.py
yaml_rulz/errors.py
yaml_rulz/list_handler.py
yaml_rulz/rulebook.py
yaml_rulz/validator.py
yaml_rulz/yaml_handler.py
yaml_rulz.egg-info/PKG-INFO
yaml_rulz.egg-info/SOURCES.txt
yaml_rulz.egg-info/dependency_links.txt
yaml_rulz.egg-info/entry_points.txt
yaml_rulz.egg-info/requires.txt
yaml_rulz.egg-info/top_level.txt