Metadata-Version: 1.1
Name: yaml-rulz
Version: 0.0.1
Summary: A YAML validator
Home-page: https://github.com/milonoir/yaml_rulz
Author: Milan Boleradszki
Author-email: bmilan1985@gmail.com
License: MIT
Platform: UNKNOWN
Classifier: Development Status :: 4 - Beta
Classifier: Environment :: Console
Classifier: Intended Audience :: System Administrators
Classifier: License :: OSI Approved :: MIT License
Classifier: Natural Language :: English
Classifier: Operating System :: Unix
Classifier: Programming Language :: Python :: 2.7
Classifier: Programming Language :: Python :: 3.5
Classifier: Topic :: Text Processing :: Markup
